[
  { "BodyId": 1, "SignId": 1 },
  { "BodyId": 1, "SignId": 2 },
  { "BodyId": 1, "SignId": 3 },
  { "BodyId": 1, "SignId": 4 },
  { "BodyId": 1, "SignId": 5 },
  { "BodyId": 1, "SignId": 6 },
  { "BodyId": 1, "SignId": 7 },
  { "BodyId": 2, "SignId": 1 },
  { "BodyId": 2, "SignId": 2 },
  { "BodyId": 2, "SignId": 3 },
  { "BodyId": 2, "SignId": 4 },
  { "BodyId": 2, "SignId": 5 },
  { "BodyId": 2, "SignId": 6 },
  { "BodyId": 2, "SignId": 7 },
  { "BodyId": 3, "SignId": 1 },
  { "BodyId": 3, "SignId": 2 },
  { "BodyId": 3, "SignId": 3 },
  { "BodyId": 3, "SignId": 4 },
  { "BodyId": 3, "SignId": 5 },
  { "BodyId": 3, "SignId": 6 },
  { "BodyId": 3, "SignId": 7 },
  { "BodyId": 4, "SignId": 1 },
  { "BodyId": 4, "SignId": 2 },
  { "BodyId": 4, "SignId": 3 },
  { "BodyId": 4, "SignId": 4 },
  { "BodyId": 4, "SignId": 5 },
  { "BodyId": 4, "SignId": 6 },
  { "BodyId": 4, "SignId": 7 },
  { "BodyId": 5, "SignId": 1 },
  { "BodyId": 5, "SignId": 2 },
  { "BodyId": 5, "SignId": 3 },
  { "BodyId": 5, "SignId": 4 },
  { "BodyId": 5, "SignId": 5 },
  { "BodyId": 5, "SignId": 6 },
  { "BodyId": 5, "SignId": 7 },
  { "BodyId": 6, "SignId": 1 },
  { "BodyId": 6, "SignId": 2 },
  { "BodyId": 6, "SignId": 3 },
  { "BodyId": 6, "SignId": 4 },
  { "BodyId": 6, "SignId": 5 },
  { "BodyId": 6, "SignId": 6 },
  { "BodyId": 6, "SignId": 7 },
  { "BodyId": 7, "SignId": 1 },
  { "BodyId": 7, "SignId": 2 },
  { "BodyId": 7, "SignId": 3 },
  { "BodyId": 7, "SignId": 4 },
  { "BodyId": 7, "SignId": 5 },
  { "BodyId": 7, "SignId": 6 },
  { "BodyId": 7, "SignId": 7 },
  { "BodyId": 8, "SignId": 1 },
  { "BodyId": 8, "SignId": 2 },
  { "BodyId": 8, "SignId": 3 },
  { "BodyId": 8, "SignId": 4 },
  { "BodyId": 8, "SignId": 5 },
  { "BodyId": 8, "SignId": 6 },
  { "BodyId": 8, "SignId": 7 },
  { "BodyId": 9, "SignId": 1 },
  { "BodyId": 9, "SignId": 2 },
  { "BodyId": 9, "SignId": 3 },
  { "BodyId": 9, "SignId": 4 },
  { "BodyId": 9, "SignId": 5 },
  { "BodyId": 9, "SignId": 6 },
  { "BodyId": 9, "SignId": 7 },
  { "BodyId": 10, "SignId": 1 },
  { "BodyId": 10, "SignId": 2 },
  { "BodyId": 10, "SignId": 3 },
  { "BodyId": 10, "SignId": 4 },
  { "BodyId": 10, "SignId": 5 },
  { "BodyId": 10, "SignId": 6 },
  { "BodyId": 10, "SignId": 7 },
  { "BodyId": 11, "SignId": 1 },
  { "BodyId": 11, "SignId": 2 },
  { "BodyId": 11, "SignId": 3 },
  { "BodyId": 11, "SignId": 4 },
  { "BodyId": 11, "SignId": 5 },
  { "BodyId": 11, "SignId": 6 },
  { "BodyId": 11, "SignId": 7 },
  { "BodyId": 12, "SignId": 1 },
  { "BodyId": 12, "SignId": 2 },
  { "BodyId": 12, "SignId": 3 },
  { "BodyId": 12, "SignId": 4 },
  { "BodyId": 12, "SignId": 5 },
  { "BodyId": 12, "SignId": 6 },
  { "BodyId": 12, "SignId": 7 }
]
